{
"meta":{"test_sets":[],"test_metrics":[],"learn_metrics":[{"best_value":"Min","name":"RMSE"}],"launch_mode":"Train","parameters":"","iteration_count":250,"learn_sets":["learn"],"name":"experiment"},
"iterations":[
{"learn":[29.45333654],"iteration":0,"passed_time":0.08922908199,"remaining_time":22.21804141},
{"learn":[27.07408127],"iteration":1,"passed_time":0.1744038093,"remaining_time":21.62607235},
{"learn":[24.96359689],"iteration":2,"passed_time":0.2649019873,"remaining_time":21.81026362},
{"learn":[23.10080456],"iteration":3,"passed_time":0.3562930711,"remaining_time":21.91202387},
{"learn":[21.42296744],"iteration":4,"passed_time":0.4502315949,"remaining_time":22.06134815},
{"learn":[19.95199838],"iteration":5,"passed_time":0.5351086917,"remaining_time":21.7610868},
{"learn":[18.63052943],"iteration":6,"passed_time":0.6202008317,"remaining_time":21.52982887},
{"learn":[17.45947295],"iteration":7,"passed_time":0.7069327545,"remaining_time":21.38471582},
{"learn":[16.39975899],"iteration":8,"passed_time":0.8018644639,"remaining_time":21.47214842},
{"learn":[15.49708786],"iteration":9,"passed_time":0.8877683157,"remaining_time":21.30643958},
{"learn":[14.69981599],"iteration":10,"passed_time":0.9723400147,"remaining_time":21.12629668},
{"learn":[13.96946992],"iteration":11,"passed_time":1.057829959,"remaining_time":20.98029419},
{"learn":[13.31824886],"iteration":12,"passed_time":1.145583372,"remaining_time":20.88486608},
{"learn":[12.77821422],"iteration":13,"passed_time":1.252152403,"remaining_time":21.10771194},
{"learn":[12.29772921],"iteration":14,"passed_time":1.376082736,"remaining_time":21.55862953},
{"learn":[11.88106845],"iteration":15,"passed_time":1.466902252,"remaining_time":21.45344543},
{"learn":[11.49207536],"iteration":16,"passed_time":1.553461813,"remaining_time":21.29156485},
{"learn":[11.17624159],"iteration":17,"passed_time":1.641163761,"remaining_time":21.15277736},
{"learn":[10.87188387],"iteration":18,"passed_time":1.739893369,"remaining_time":21.15344043},
{"learn":[10.62550165],"iteration":19,"passed_time":1.833102508,"remaining_time":21.08067884},
{"learn":[10.3987359],"iteration":20,"passed_time":1.921167126,"remaining_time":20.94987009},
{"learn":[10.20253593],"iteration":21,"passed_time":2.001885784,"remaining_time":20.74681631},
{"learn":[10.03361619],"iteration":22,"passed_time":2.085205909,"remaining_time":20.58007571},
{"learn":[9.871062649],"iteration":23,"passed_time":2.176448748,"remaining_time":20.49489237},
{"learn":[9.691276016],"iteration":24,"passed_time":2.257538566,"remaining_time":20.3178471},
{"learn":[9.546657453],"iteration":25,"passed_time":2.356294088,"remaining_time":20.30037984},
{"learn":[9.420574766],"iteration":26,"passed_time":2.464559279,"remaining_time":20.35543404},
{"learn":[9.312368419],"iteration":27,"passed_time":2.547297459,"remaining_time":20.19642985},
{"learn":[9.210857109],"iteration":28,"passed_time":2.632055697,"remaining_time":20.05807962},
{"learn":[9.125094124],"iteration":29,"passed_time":2.718850035,"remaining_time":19.93823359},
{"learn":[9.053433057],"iteration":30,"passed_time":2.800275452,"remaining_time":19.7825911},
{"learn":[8.970285382],"iteration":31,"passed_time":2.884220631,"remaining_time":19.64875305},
{"learn":[8.890220313],"iteration":32,"passed_time":2.969198091,"remaining_time":19.52472684},
{"learn":[8.819796078],"iteration":33,"passed_time":3.053256697,"remaining_time":19.39716019},
{"learn":[8.765105958],"iteration":34,"passed_time":3.140961652,"remaining_time":19.29447872},
{"learn":[8.714712911],"iteration":35,"passed_time":3.239551462,"remaining_time":19.25733369},
{"learn":[8.662291917],"iteration":36,"passed_time":3.326452117,"remaining_time":19.1495757},
{"learn":[8.618982372],"iteration":37,"passed_time":3.41328411,"remaining_time":19.0425324},
{"learn":[8.565900116],"iteration":38,"passed_time":3.501211337,"remaining_time":18.94245108},
{"learn":[8.52967232],"iteration":39,"passed_time":3.58805804,"remaining_time":18.83730471},
{"learn":[8.46771374],"iteration":40,"passed_time":3.67061022,"remaining_time":18.71115941},
{"learn":[8.431258835],"iteration":41,"passed_time":3.754563818,"remaining_time":18.59403034},
{"learn":[8.395290001],"iteration":42,"passed_time":3.837077869,"remaining_time":18.47151439},
{"learn":[8.353985424],"iteration":43,"passed_time":3.919973657,"remaining_time":18.35260394},
{"learn":[8.323306521],"iteration":44,"passed_time":4.008574779,"remaining_time":18.2612851},
{"learn":[8.275096712],"iteration":45,"passed_time":4.094026866,"remaining_time":18.15611914},
{"learn":[8.248875564],"iteration":46,"passed_time":4.178129967,"remaining_time":18.0459656},
{"learn":[8.225038778],"iteration":47,"passed_time":4.264195473,"remaining_time":17.94515595},
{"learn":[8.192796411],"iteration":48,"passed_time":4.348483266,"remaining_time":17.83765585},
{"learn":[8.155701335],"iteration":49,"passed_time":4.432203979,"remaining_time":17.72881592},
{"learn":[8.134684809],"iteration":50,"passed_time":4.517859381,"remaining_time":17.62851013},
{"learn":[8.103769661],"iteration":51,"passed_time":4.59932605,"remaining_time":17.51281842},
{"learn":[8.073901825],"iteration":52,"passed_time":4.680221757,"remaining_time":17.39629597},
{"learn":[8.050707649],"iteration":53,"passed_time":4.763479558,"remaining_time":17.28966654},
{"learn":[8.025721345],"iteration":54,"passed_time":4.846368045,"remaining_time":17.18257762},
{"learn":[7.996986001],"iteration":55,"passed_time":4.933175119,"remaining_time":17.08992809},
{"learn":[7.965255241],"iteration":56,"passed_time":5.02372591,"remaining_time":17.01015966},
{"learn":[7.94709617],"iteration":57,"passed_time":5.111123464,"remaining_time":16.91958112},
{"learn":[7.924348858],"iteration":58,"passed_time":5.195976407,"remaining_time":16.82087278},
{"learn":[7.901639412],"iteration":59,"passed_time":5.31965462,"remaining_time":16.84557296},
{"learn":[7.887834833],"iteration":60,"passed_time":5.447451724,"remaining_time":16.8781701},
{"learn":[7.871795025],"iteration":61,"passed_time":5.564713578,"remaining_time":16.87364762},
{"learn":[7.846046783],"iteration":62,"passed_time":5.666441282,"remaining_time":16.81943682},
{"learn":[7.823418668],"iteration":63,"passed_time":5.766910272,"remaining_time":16.76008298},
{"learn":[7.801194529],"iteration":64,"passed_time":5.883499497,"remaining_time":16.74534472},
{"learn":[7.782679637],"iteration":65,"passed_time":6.00114501,"remaining_time":16.73046488},
{"learn":[7.767776672],"iteration":66,"passed_time":6.086349727,"remaining_time":16.62391045},
{"learn":[7.723637618],"iteration":67,"passed_time":6.170085648,"remaining_time":16.51405276},
{"learn":[7.704556889],"iteration":68,"passed_time":6.370384598,"remaining_time":16.71071902},
{"learn":[7.681886677],"iteration":69,"passed_time":6.514536567,"remaining_time":16.75166546},
{"learn":[7.659661139],"iteration":70,"passed_time":6.638842876,"remaining_time":16.73736443},
{"learn":[7.637914065],"iteration":71,"passed_time":6.748498709,"remaining_time":16.68378848},
{"learn":[7.616643911],"iteration":72,"passed_time":6.877246697,"remaining_time":16.67496802},
{"learn":[7.598637903],"iteration":73,"passed_time":6.968890619,"remaining_time":16.57465877},
{"learn":[7.588941957],"iteration":74,"passed_time":7.057753841,"remaining_time":16.4680923},
{"learn":[7.572652029],"iteration":75,"passed_time":7.143436862,"remaining_time":16.35471071},
{"learn":[7.555514963],"iteration":76,"passed_time":7.223566852,"remaining_time":16.22957228},
{"learn":[7.54532904],"iteration":77,"passed_time":7.307472667,"remaining_time":16.11391409},
{"learn":[7.529446087],"iteration":78,"passed_time":7.389442996,"remaining_time":15.99487028},
{"learn":[7.513117353],"iteration":79,"passed_time":7.474747078,"remaining_time":15.88383754},
{"learn":[7.50181626],"iteration":80,"passed_time":7.556960863,"remaining_time":15.76699242},
{"learn":[7.491761135],"iteration":81,"passed_time":7.644838795,"remaining_time":15.66259656},
{"learn":[7.47865215],"iteration":82,"passed_time":7.724464245,"remaining_time":15.54199432},
{"learn":[7.467104744],"iteration":83,"passed_time":7.807909653,"remaining_time":15.42991669},
{"learn":[7.434618129],"iteration":84,"passed_time":7.903687823,"remaining_time":15.34245283},
{"learn":[7.42597988],"iteration":85,"passed_time":7.999341218,"remaining_time":15.25455767},
{"learn":[7.40919477],"iteration":86,"passed_time":8.097917668,"remaining_time":15.17196069},
{"learn":[7.374161593],"iteration":87,"passed_time":8.188051577,"remaining_time":15.07345858},
{"learn":[7.347131997],"iteration":88,"passed_time":8.267042096,"remaining_time":14.95498626},
{"learn":[7.323647858],"iteration":89,"passed_time":8.349085927,"remaining_time":14.84281942},
{"learn":[7.312435365],"iteration":90,"passed_time":8.431116039,"remaining_time":14.73129066},
{"learn":[7.291833375],"iteration":91,"passed_time":8.509649444,"remaining_time":14.61439796},
{"learn":[7.280973025],"iteration":92,"passed_time":8.59310736,"remaining_time":14.50664361},
{"learn":[7.267819011],"iteration":93,"passed_time":8.676483927,"remaining_time":14.3992712},
{"learn":[7.256664797],"iteration":94,"passed_time":8.757249581,"remaining_time":14.28814405},
{"learn":[7.246451724],"iteration":95,"passed_time":8.837588579,"remaining_time":14.17696501},
{"learn":[7.233978103],"iteration":96,"passed_time":8.919949279,"remaining_time":14.06961072},
{"learn":[7.220651058],"iteration":97,"passed_time":8.999017717,"remaining_time":13.95766013},
{"learn":[7.193645583],"iteration":98,"passed_time":9.081571376,"remaining_time":13.85168967},
{"learn":[7.179370599],"iteration":99,"passed_time":9.163495083,"remaining_time":13.74524262},
{"learn":[7.161270355],"iteration":100,"passed_time":9.244061892,"remaining_time":13.63727942},
{"learn":[7.146985757],"iteration":101,"passed_time":9.329485585,"remaining_time":13.53690065},
{"learn":[7.131686385],"iteration":102,"passed_time":9.421836392,"remaining_time":13.44669854},
{"learn":[7.120614438],"iteration":103,"passed_time":9.50244906,"remaining_time":13.33997656},
{"learn":[7.097561877],"iteration":104,"passed_time":9.584992681,"remaining_time":13.23641846},
{"learn":[7.088005378],"iteration":105,"passed_time":9.668920912,"remaining_time":13.13513784},
{"learn":[7.064194571],"iteration":106,"passed_time":9.747750444,"remaining_time":13.02736742},
{"learn":[7.049342794],"iteration":107,"passed_time":9.831057438,"remaining_time":12.92601997},
{"learn":[7.03087038],"iteration":108,"passed_time":9.913323618,"remaining_time":12.82365716},
{"learn":[7.018568699],"iteration":109,"passed_time":9.99426737,"remaining_time":12.71997665},
{"learn":[7.008178671],"iteration":110,"passed_time":10.07623498,"remaining_time":12.61798795},
{"learn":[6.995057523],"iteration":111,"passed_time":10.16128739,"remaining_time":12.52015768},
{"learn":[6.978065392],"iteration":112,"passed_time":10.24133356,"remaining_time":12.41648405},
{"learn":[6.958533482],"iteration":113,"passed_time":10.32559236,"remaining_time":12.31825053},
{"learn":[6.941944674],"iteration":114,"passed_time":10.41004712,"remaining_time":12.2204901},
{"learn":[6.924803366],"iteration":115,"passed_time":10.49602058,"remaining_time":12.12471343},
{"learn":[6.902904137],"iteration":116,"passed_time":10.57639476,"remaining_time":12.02273935},
{"learn":[6.893388708],"iteration":117,"passed_time":10.65901231,"remaining_time":11.92364089},
{"learn":[6.878480879],"iteration":118,"passed_time":10.739276,"remaining_time":11.8222282},
{"learn":[6.869665999],"iteration":119,"passed_time":10.82185004,"remaining_time":11.72367087},
{"learn":[6.849644981],"iteration":120,"passed_time":10.9047141,"remaining_time":11.62568693},
{"learn":[6.837400315],"iteration":121,"passed_time":10.98923511,"remaining_time":11.52968929},
{"learn":[6.823926739],"iteration":122,"passed_time":11.06819988,"remaining_time":11.42814134},
{"learn":[6.815008035],"iteration":123,"passed_time":11.1522064,"remaining_time":11.3320807},
{"learn":[6.80272776],"iteration":124,"passed_time":11.2384173,"remaining_time":11.2384173},
{"learn":[6.789468657],"iteration":125,"passed_time":11.32179708,"remaining_time":11.14208601},
{"learn":[6.773682578],"iteration":126,"passed_time":11.40936891,"remaining_time":11.05001871},
{"learn":[6.758343976],"iteration":127,"passed_time":11.49490582,"remaining_time":10.95608211},
{"learn":[6.75045436],"iteration":128,"passed_time":11.57614369,"remaining_time":10.8582433},
{"learn":[6.733279709],"iteration":129,"passed_time":11.65687166,"remaining_time":10.76018922},
{"learn":[6.723873802],"iteration":130,"passed_time":11.73804724,"remaining_time":10.66280627},
{"learn":[6.713755748],"iteration":131,"passed_time":11.81922302,"remaining_time":10.56566906},
{"learn":[6.705062326],"iteration":132,"passed_time":11.90760533,"remaining_time":10.47511146},
{"learn":[6.688528989],"iteration":133,"passed_time":11.99680904,"remaining_time":10.38529738},
{"learn":[6.676243216],"iteration":134,"passed_time":12.07989627,"remaining_time":10.29028201},
{"learn":[6.6634821],"iteration":135,"passed_time":12.16402283,"remaining_time":10.19631326},
{"learn":[6.655207818],"iteration":136,"passed_time":12.24767957,"remaining_time":10.10210066},
{"learn":[6.639981115],"iteration":137,"passed_time":12.3296993,"remaining_time":10.00671248},
{"learn":[6.622404596],"iteration":138,"passed_time":12.4200442,"remaining_time":9.918164793},
{"learn":[6.609583374],"iteration":139,"passed_time":12.5057863,"remaining_time":9.825974953},
{"learn":[6.588789624],"iteration":140,"passed_time":12.58739079,"remaining_time":9.730677984},
{"learn":[6.577690803],"iteration":141,"passed_time":12.67220463,"remaining_time":9.638014788},
{"learn":[6.562164484],"iteration":142,"passed_time":12.75368778,"remaining_time":9.542969177},
{"learn":[6.554036092],"iteration":143,"passed_time":12.83147047,"remaining_time":9.445387986},
{"learn":[6.541680184],"iteration":144,"passed_time":12.91601669,"remaining_time":9.352977601},
{"learn":[6.527507086],"iteration":145,"passed_time":12.99503503,"remaining_time":9.256737279},
{"learn":[6.518315246],"iteration":146,"passed_time":13.07733488,"remaining_time":9.163030565},
{"learn":[6.503964143],"iteration":147,"passed_time":13.17296522,"remaining_time":9.07866522},
{"learn":[6.491138627],"iteration":148,"passed_time":13.25561076,"remaining_time":8.98534689},
{"learn":[6.482781855],"iteration":149,"passed_time":13.33526692,"remaining_time":8.890177948},
{"learn":[6.47028735],"iteration":150,"passed_time":13.4201702,"remaining_time":8.798654633},
{"learn":[6.46109809],"iteration":151,"passed_time":13.50258628,"remaining_time":8.70561484},
{"learn":[6.451979804],"iteration":152,"passed_time":13.58182075,"remaining_time":8.610696817},
{"learn":[6.442840987],"iteration":153,"passed_time":13.66657176,"remaining_time":8.51942136},
{"learn":[6.436228988],"iteration":154,"passed_time":13.74779002,"remaining_time":8.426064848},
{"learn":[6.427975672],"iteration":155,"passed_time":13.82851003,"remaining_time":8.332563738},
{"learn":[6.420370634],"iteration":156,"passed_time":13.91591715,"remaining_time":8.243186589},
{"learn":[6.406964873],"iteration":157,"passed_time":13.99697191,"remaining_time":8.150135543},
{"learn":[6.392907469],"iteration":158,"passed_time":14.07498303,"remaining_time":8.055493432},
{"learn":[6.377535127],"iteration":159,"passed_time":14.15595868,"remaining_time":7.962726757},
{"learn":[6.363479522],"iteration":160,"passed_time":14.23639856,"remaining_time":7.869810385},
{"learn":[6.350812603],"iteration":161,"passed_time":14.31704373,"remaining_time":7.777159559},
{"learn":[6.339684368],"iteration":162,"passed_time":14.39797392,"remaining_time":7.684808167},
{"learn":[6.332639948],"iteration":163,"passed_time":14.48166464,"remaining_time":7.594043651},
{"learn":[6.32057898],"iteration":164,"passed_time":14.55967217,"remaining_time":7.500437176},
{"learn":[6.31447512],"iteration":165,"passed_time":14.64153682,"remaining_time":7.408970438},
{"learn":[6.305410788],"iteration":166,"passed_time":14.72278211,"remaining_time":7.31731087},
{"learn":[6.296823467],"iteration":167,"passed_time":14.81153269,"remaining_time":7.229438575},
{"learn":[6.287024397],"iteration":168,"passed_time":14.9036081,"remaining_time":7.143149444},
{"learn":[6.278417523],"iteration":169,"passed_time":14.99001662,"remaining_time":7.054125468},
{"learn":[6.269726941],"iteration":170,"passed_time":15.07073293,"remaining_time":6.962502349},
{"learn":[6.259031595],"iteration":171,"passed_time":15.15392022,"remaining_time":6.87212661},
{"learn":[6.250663272],"iteration":172,"passed_time":15.23760272,"remaining_time":6.782054392},
{"learn":[6.243274808],"iteration":173,"passed_time":15.31853175,"remaining_time":6.690852949},
{"learn":[6.235869168],"iteration":174,"passed_time":15.40485152,"remaining_time":6.602079223},
{"learn":[6.226997059],"iteration":175,"passed_time":15.49061433,"remaining_time":6.513099207},
{"learn":[6.221151418],"iteration":176,"passed_time":15.56915796,"remaining_time":6.421178142},
{"learn":[6.215365373],"iteration":177,"passed_time":15.64986518,"remaining_time":6.330282543},
{"learn":[6.205590358],"iteration":178,"passed_time":15.72961349,"remaining_time":6.239120434},
{"learn":[6.196080536],"iteration":179,"passed_time":15.80936489,"remaining_time":6.148086347},
{"learn":[6.188487942],"iteration":180,"passed_time":15.89488153,"remaining_time":6.059374727},
{"learn":[6.181470055],"iteration":181,"passed_time":15.97618222,"remaining_time":5.969123027},
{"learn":[6.176049704],"iteration":182,"passed_time":16.05737434,"remaining_time":5.878929405},
{"learn":[6.166808527],"iteration":183,"passed_time":16.14478839,"remaining_time":5.791065402},
{"learn":[6.15760555],"iteration":184,"passed_time":16.22782029,"remaining_time":5.701666587},
{"learn":[6.150729999],"iteration":185,"passed_time":16.31492677,"remaining_time":5.613738243},
{"learn":[6.141490553],"iteration":186,"passed_time":16.40380203,"remaining_time":5.526414588},
{"learn":[6.131524252],"iteration":187,"passed_time":16.48389702,"remaining_time":5.436178806},
{"learn":[6.122055577],"iteration":188,"passed_time":16.56623543,"remaining_time":5.346774399},
{"learn":[6.11435332],"iteration":189,"passed_time":16.65152162,"remaining_time":5.258375248},
{"learn":[6.102919944],"iteration":190,"passed_time":16.73836758,"remaining_time":5.170490509},
{"learn":[6.095000596],"iteration":191,"passed_time":16.83792682,"remaining_time":5.08645706},
{"learn":[6.080908282],"iteration":192,"passed_time":16.91993313,"remaining_time":4.997078698},
{"learn":[6.073574835],"iteration":193,"passed_time":17.00067162,"remaining_time":4.907410364},
{"learn":[6.064189835],"iteration":194,"passed_time":17.07922501,"remaining_time":4.817217311},
{"learn":[6.056071527],"iteration":195,"passed_time":17.16096488,"remaining_time":4.728020937},
{"learn":[6.049825104],"iteration":196,"passed_time":17.23860847,"remaining_time":4.637798218},
{"learn":[6.042898374],"iteration":197,"passed_time":17.32009182,"remaining_time":4.548710983},
{"learn":[6.034743108],"iteration":198,"passed_time":17.41633196,"remaining_time":4.463482061},
{"learn":[6.027960614],"iteration":199,"passed_time":17.50773131,"remaining_time":4.376932827},
{"learn":[6.021262715],"iteration":200,"passed_time":17.58901743,"remaining_time":4.287869921},
{"learn":[6.011840769],"iteration":201,"passed_time":17.67447188,"remaining_time":4.199874507},
{"learn":[6.00639223],"iteration":202,"passed_time":17.75528707,"remaining_time":4.110830012},
{"learn":[5.997619701],"iteration":203,"passed_time":17.83793885,"remaining_time":4.022280329},
{"learn":[5.990409245],"iteration":204,"passed_time":17.92296109,"remaining_time":3.934308532},
{"learn":[5.980169352],"iteration":205,"passed_time":18.00717518,"remaining_time":3.846192757},
{"learn":[5.972611234],"iteration":206,"passed_time":18.09184769,"remaining_time":3.758209906},
{"learn":[5.966676187],"iteration":207,"passed_time":18.18040746,"remaining_time":3.671043814},
{"learn":[5.961648194],"iteration":208,"passed_time":18.26070063,"remaining_time":3.582242708},
{"learn":[5.954781712],"iteration":209,"passed_time":18.34006569,"remaining_time":3.493345845},
{"learn":[5.94498374],"iteration":210,"passed_time":18.42265806,"remaining_time":3.40513585},
{"learn":[5.936901664],"iteration":211,"passed_time":18.5007639,"remaining_time":3.316174662},
{"learn":[5.926619091],"iteration":212,"passed_time":18.57865959,"remaining_time":3.227278896},
{"learn":[5.92132312],"iteration":213,"passed_time":18.66335976,"remaining_time":3.139630614},
{"learn":[5.917070595],"iteration":214,"passed_time":18.74171384,"remaining_time":3.050976672},
{"learn":[5.908542391],"iteration":215,"passed_time":18.82630377,"remaining_time":2.963399668},
{"learn":[5.902825624],"iteration":216,"passed_time":18.91018996,"remaining_time":2.875743174},
{"learn":[5.895479983],"iteration":217,"passed_time":18.99849292,"remaining_time":2.788769602},
{"learn":[5.888982535],"iteration":218,"passed_time":19.081987,"remaining_time":2.701103183},
{"learn":[5.883289738],"iteration":219,"passed_time":19.16894009,"remaining_time":2.613946376},
{"learn":[5.872660339],"iteration":220,"passed_time":19.25543956,"remaining_time":2.526731888},
{"learn":[5.866588222],"iteration":221,"passed_time":19.34270766,"remaining_time":2.439620787},
{"learn":[5.861395056],"iteration":222,"passed_time":19.4292567,"remaining_time":2.352421215},
{"learn":[5.852597888],"iteration":223,"passed_time":19.5130514,"remaining_time":2.264907752},
{"learn":[5.847084366],"iteration":224,"passed_time":19.59658833,"remaining_time":2.177398704},
{"learn":[5.840251818],"iteration":225,"passed_time":19.68340811,"remaining_time":2.090273427},
{"learn":[5.832769342],"iteration":226,"passed_time":19.76658725,"remaining_time":2.002781968},
{"learn":[5.827620116],"iteration":227,"passed_time":19.85031199,"remaining_time":1.915380982},
{"learn":[5.819457647],"iteration":228,"passed_time":19.93858564,"remaining_time":1.828429251},
{"learn":[5.811048916],"iteration":229,"passed_time":20.02126053,"remaining_time":1.740979177},
{"learn":[5.804009781],"iteration":230,"passed_time":20.10027297,"remaining_time":1.653269205},
{"learn":[5.798466526],"iteration":231,"passed_time":20.18818222,"remaining_time":1.566324482},
{"learn":[5.792746917],"iteration":232,"passed_time":20.26984045,"remaining_time":1.478915398},
{"learn":[5.783747468],"iteration":233,"passed_time":20.35189063,"remaining_time":1.391582265},
{"learn":[5.776262929],"iteration":234,"passed_time":20.43555034,"remaining_time":1.30439683},
{"learn":[5.766738191],"iteration":235,"passed_time":20.51398451,"remaining_time":1.216931285},
{"learn":[5.760775205],"iteration":236,"passed_time":20.59256527,"remaining_time":1.129549994},
{"learn":[5.755707792],"iteration":237,"passed_time":20.67573458,"remaining_time":1.042474012},
{"learn":[5.748839484],"iteration":238,"passed_time":20.75863097,"remaining_time":0.9554181616},
{"learn":[5.74219048],"iteration":239,"passed_time":20.84831108,"remaining_time":0.8686796281},
{"learn":[5.735114371],"iteration":240,"passed_time":20.9316184,"remaining_time":0.7816786953},
{"learn":[5.727728552],"iteration":241,"passed_time":21.01093423,"remaining_time":0.6945763383},
{"learn":[5.72280512],"iteration":242,"passed_time":21.08852395,"remaining_time":0.6074883443},
{"learn":[5.715192132],"iteration":243,"passed_time":21.17175422,"remaining_time":0.520616907},
{"learn":[5.709983745],"iteration":244,"passed_time":21.24975864,"remaining_time":0.4336685437},
{"learn":[5.702090113],"iteration":245,"passed_time":21.32801898,"remaining_time":0.3467970565},
{"learn":[5.696555647],"iteration":246,"passed_time":21.41298009,"remaining_time":0.2600766813},
{"learn":[5.69226241],"iteration":247,"passed_time":21.49477422,"remaining_time":0.1733449534},
{"learn":[5.685303924],"iteration":248,"passed_time":21.57595547,"remaining_time":0.08665042357},
{"learn":[5.680302919],"iteration":249,"passed_time":21.65694844,"remaining_time":0}
]}